fdsnnetextender/__init__.py
fdsnnetextender/fdsnnetextender.py
fdsnnetextender-5.0.2.dist-info/WHEEL
fdsnnetextender-5.0.2.dist-info/METADATA
fdsnnetextender-5.0.2.dist-info/RECORD
