Metadata-Version: 2.4
Name: fdsnnetextender
Version: 5.0.2
Summary: Library to determine the extended seismological network code from FDSN web service
License-Expression: GPL-3.0-or-later
Requires-Python: >=3.10
Project-URL: Home Page, https://gricad-gitlab.univ-grenoble-alpes.fr/OSUG/RESIF/fdsnnetextender
